MANIFEST.in
README.md
requirements.txt
setup.py
Elefant.egg-info/PKG-INFO
Elefant.egg-info/SOURCES.txt
Elefant.egg-info/dependency_links.txt
Elefant.egg-info/top_level.txt
elefant/__init__.py