Metadata-Version: 1.1
Name: Elefant
Version: 0.0.4
Summary: Backing up and restoring Postgres databases using S3 for automation
Home-page: http://packages.python.org/elefant
Author: Will Drevo
Author-email: will.drevo@gmail.com
License: MIT
Keywords: python heroku postgres backup s3
Platform: UNKNOWN
Classifier: Development Status :: 3 - Alpha
Classifier: Topic :: Utilities
Classifier: License :: OSI Approved :: MIT License
